mtf/__init__.py
te_mtf-0.0.1.dist-info/licenses/LICENSE
te_mtf-0.0.1.dist-info/METADATA
te_mtf-0.0.1.dist-info/WHEEL
te_mtf-0.0.1.dist-info/top_level.txt
te_mtf-0.0.1.dist-info/RECORD
