Metadata-Version: 2.4
Name: te-mtf
Version: 0.0.1
Summary: Modular Test Framework (MTF) is a testing framework designed for creating, executing and validating tests
Author-email: Technica Engineering GmbH <mtf.support@technica-engineering.de>
Project-URL: Homepage, https://technica-engineering.de/en/
Classifier: Programming Language :: Python :: 3
Classifier: License :: OSI Approved :: MIT License
Classifier: Operating System :: OS Independent
Requires-Python: >=3.10
License-File: LICENSE
Requires-Dist: rich>=13.0.0
Dynamic: license-file
